HISTORY.rst
LICENSE
MANIFEST.in
README.rst
setup.py
durant/__init__.py
durant/__main__.py
durant/cli.py
durant/colors.py
durant/config.py
durant/exceptions.py
durant/main.py
durant.egg-info/PKG-INFO
durant.egg-info/SOURCES.txt
durant.egg-info/dependency_links.txt
durant.egg-info/entry_points.txt
durant.egg-info/not-zip-safe
durant.egg-info/requires.txt
durant.egg-info/top_level.txt