Metadata-Version: 1.1
Name: durant
Version: 0.2.3
Summary: Simple git deployment tool
Home-page: https://github.com/misterjinx/durant
Author: Marius Bărbulescu
Author-email: marius@freshcolors.ro
License: Apache 2.0
Platform: linux
Classifier: Development Status :: 4 - Beta
Classifier: Environment :: Console
Classifier: Intended Audience :: Developers
Classifier: Intended Audience :: System Administrators
Classifier: License :: OSI Approved :: Apache Software License
Classifier: Programming Language :: Python
Classifier: Programming Language :: Python :: 2.6
Classifier: Programming Language :: Python :: 2.7
Classifier: Programming Language :: Python :: 3
Classifier: Programming Language :: Python :: 3.3
Classifier: Programming Language :: Python :: 3.4
